mongodb_typegen/cli.py
mongodb_typegen-1.1.0.dist-info/METADATA
mongodb_typegen-1.1.0.dist-info/WHEEL
mongodb_typegen-1.1.0.dist-info/entry_points.txt
mongodb_typegen-1.1.0.dist-info/licenses/LICENSE
mongodb_typegen-1.1.0.dist-info/RECORD
