Metadata-Version: 2.4
Name: mongodb-typegen
Version: 1.1.0
Summary: A CLI tool to generate Python TypedDict models from a MongoDB database.
Project-URL: Homepage, https://github.com/raprocks/mongodb-typegen
Project-URL: Bug Tracker, https://github.com/raprocks/mongodb-typegen/issues
Project-URL: Repository, https://github.com/raprocks/mongodb-typegen
Author-email: Rohit Patil <rahulhimesh09@gmail.com>
License: MIT
License-File: LICENSE
Keywords: codegen,mongodb,odm,pymongo,type-generation,typeddict
Classifier: Development Status :: 5 - Production/Stable
Classifier: Intended Audience :: Developers
Classifier: License :: OSI Approved :: MIT License
Classifier: Operating System :: OS Independent
Classifier: Programming Language :: Python :: 3
Classifier: Programming Language :: Python :: 3.8
Classifier: Programming Language :: Python :: 3.9
Classifier: Programming Language :: Python :: 3.10
Classifier: Programming Language :: Python :: 3.11
Classifier: Programming Language :: Python :: 3.12
Classifier: Topic :: Database
Classifier: Topic :: Software Development :: Code Generators
Classifier: Topic :: Utilities
Requires-Python: >=3.8
Requires-Dist: click
Requires-Dist: pymongo[srv]
Provides-Extra: test
Requires-Dist: pytest; extra == 'test'
Requires-Dist: pytest-mock; extra == 'test'
